pdftoxlsx_v1/__init__.py
pdftoxlsx_v1/transt.py
pdftoxlsx_v1-1.0.1.dist-info/LICENSE
pdftoxlsx_v1-1.0.1.dist-info/METADATA
pdftoxlsx_v1-1.0.1.dist-info/WHEEL
pdftoxlsx_v1-1.0.1.dist-info/top_level.txt
pdftoxlsx_v1-1.0.1.dist-info/RECORD
